<?xml version="1.0" encoding="UTF-8"?>
<translations version="12.10_0"><t><key>allRightsReserved</key><val>iSoftBet All Rights Reserved.</val></t><t><key>alreadyLoggedInThisGame</key><val>It looks like you already have this game open. Please check or log out and back in to fix the issue.</val></t><t><key>autoPlayInfoBoxMessage</key><val>AUTO SPINS: {1} of {2}</val></t><t><key>autoplaySettingsAdvancedSettings</key><val>ADVANCED SETTINGS</val></t><t><key>autoplaySettingsConditionCreditDescription</key><val>SET LOSS LIMIT:</val></t><t><key>autoplaySettingsConditionJackpotDescription</key><val>IF A FEATURE IS WON</val></t><t><key>autoplaySettingsConditionWinDescription</key><val>IF A WIN REACHES:</val></t><t><key>autoplaySettingsStopAutoSpin</key><val>STOP AUTO SPINS:</val></t><t><key>autoplaySettingsWindowActivateButtonLabel</key><val>ACTIVATE</val></t><t><key>autoplaySettingsWindowCancelButtonLabel</key><val>CANCEL</val></t><t><key>autoplaySettingsWindowCreditDescription</key><val>LOSS LIMIT:</val></t><t><key>autoplaySettingsWindowJackpotDescription</key><val>STOP IF JACKPOT IS WON</val></t><t><key>autoplaySettingsWindowStartButtonLabel</key><val>START</val></t><t><key>autoplaySettingsWindowTitle</key><val>AUTO SPIN</val></t><t><key>autoplaySettingsWindowTotalGamesDescription</key><val>NUMBER OF AUTO SPINS:</val></t><t><key>autoplaySettingsWindowWinDescription</key><val>STOP IF A WIN REACHES:</val></t><t><key>autoplaySpinSettingsTitle</key><val>SPIN SETTINGS</val></t><t><key>AztecGoldCashRespins_description1</key><val>Get 5 Sun Disc Scatters to trigger the Aztec Gold Cash Respins feature.
Start with 3 Aztec Gold Cash Respins and if another Sun Disc Scatter lands in view the number of respins will reset to 3.
Watch out for the Mini, Major and Mega Sun Disc Scatters for even bigger wins.
Fill an entire reel to activate the multiplier for all Sun Disc Scatters on that reel.
When the Aztec Gold Cash Respins end all Sun Disc Scatter values in view will be paid.
Sun Disc values will be multiplied by Total Bet.</val></t><t><key>betNotValidBetMinButtonLabel</key><val>PLACE MIN. BET</val></t><t><key>betNotValidCancelButtonLabel</key><val>CANCEL</val></t><t><key>betNotValidWindowMessage</key><val>You don't have enough money to place the selected bet.</val></t><t><key>betterLuckMessage</key><val>Better luck next time!</val></t><t><key>bonus1OneByOneWin</key><val>BONUS = {1}</val></t><t><key>bonus1ShowAll</key><val>BONUS</val></t><t><key>bonus1ShowAllAfter</key><val>BONUS</val></t><t><key>bonusSystemPopupBonusNoWin</key><val>Your bonus is now completed with no winnings.</val></t><t><key>bonusSystemPopupBonusThreshold</key><val>Your bonus balance dropped below the threshold.
We had to finish your bonus.
You lost {1} of your bonus money.</val></t><t><key>bonusSystemPopupBonusThresholdNoLoss</key><val>The bonus balance reached the threshold.
We had to finish your bonus.</val></t><t><key>bonusSystemPopupBonusWin</key><val>Your bonus is now completed.
{1} of bonus money has been converted into cash.</val></t><t><key>CascadingWins_Description1</key><val>Every winning symbol is part of a reaction and is replaced by cascading symbols from above the reels.</val></t><t><key>coins</key><val>COINS</val></t><t><key>companyLabel</key><val>AN ISOFTBET GAME</val></t><t><key>connectionTimeout</key><val>Your previous session was closed for safety due to inactivity. Please refresh or reload the game to continue playing.</val></t><t><key>continueButtonLabel</key><val>CONTINUE</val></t><t><key>continueButtonLabel_MOBILE</key><val>Press anywhere to continue</val></t><t><key>credit</key><val>CREDIT</val></t><t><key>dialogWindowCloseLabel</key><val>Close</val></t><t><key>dialogWindowOkLabel</key><val>OK</val></t><t><key>dialogWindowReloadGameLabel</key><val>RELOAD</val></t><t><key>errorCode0</key><val>Username or Password not recognised. Please check your details and try again, or contact us for assistance.</val></t><t><key>errorCode1</key><val>Sorry, we seem to be having some issues with this game. Please try another while we investigate the problem.</val></t><t><key>errorCode101</key><val>Sorry, we have encountered a general network error. Please check your settings or try again later.</val></t><t><key>errorCode102</key><val>Sorry, we are having problems loading the game. Please refresh or try again later if the error persists.</val></t><t><key>errorCode103</key><val>Sorry, we have encountered a general script error. Please reload the game or try again later.</val></t><t><key>errorCode12</key><val>Sorry, that command is not recognised. Please check settings are correct and try again.</val></t><t><key>errorCode17</key><val>Sorry, we are having problems with the IP address. Please check your user settings and try again.</val></t><t><key>errorCode18</key><val>Sorry, we are having problems with the server. Please reload the game or try again later if the error persists</val></t><t><key>errorCode4</key><val>Your session has been interrupted due to poor or no signal. Please check your connection settings and try again.</val></t><t><key>errorCode5</key><val>Sorry, we are having problems connecting with the server. Please reload the game or try again later if the error persists</val></t><t><key>errorCode7</key><val>Sorry, we are having problems with the settings. Please reload the game or try again later if the error persists.</val></t><t><key>errorGameBlocked</key><val>Sorry, this game is currently unavailable. Please reload the game or try another if the error persists.</val></t><t><key>errorServerIssue</key><val>An error occured while trying to connect to the server. Please reload.</val></t><t><key>errorWindowTitle</key><val>ERROR</val></t><t><key>freeRoundCounterLabel</key><val>FREE ROUNDS: {1}</val></t><t><key>freeRoundPopupLine1End</key><val>You have won {1} during free rounds.
Your free rounds have been completed.</val></t><t><key>freeRoundPopupSpinTillYouWin</key><val>You can now SPIN TILL YOU WIN {1}.</val></t><t><key>freeRoundPopupSpinTillYouWinDisplayCapNo</key><val>Start spinning to claim your Free Rounds Bonus!</val></t><t><key>freeRoundPopupSpinTillYouWinDisplayCapYes</key><val>You can win {1}!
Start spinning to claim your Free Rounds Bonus!</val></t><t><key>freeRoundsCongratulationsLabel</key><val>CONGRATULATIONS</val></t><t><key>freeRoundsEndBonusMoneyActive</key><val>You have won {1} in bonus money from free rounds.
You are now entering real mode again.
Your balance will be reset to the state it was before.
Your bonus money has now been credited into your bonus balance.</val></t><t><key>freeRoundsEndBonusMoneyActiveNotActive</key><val>You have won {1} in bonus money from free rounds.
You are now entering real mode again.
Your balance will be reset to the state it was before.
Your bonus money is waiting for your current active bonus to be consumed or finished.</val></t><t><key>freeRoundsEndBonusMoneyPending</key><val>You have won {1} in bonus money from free rounds.
You are now entering real mode again.
Your balance will be reset to the state it was before.
To get your bonus money credited, please go to cashier and accept the bonus currently in pending.</val></t><t><key>freeRoundsEndBonusMoneyPendingAmount</key><val>You have won {1} in bonus money from free rounds. This bonus is now pending.
Please go to cashier and accept the bonus of {2} currently in pending.
Your balance will be reset to the state it was before.</val></t><t><key>freeRoundsEndBonusMoneyQueuedAmount</key><val>You have won {1} in bonus money from free rounds. This bonus is now in queue.
Please play your current active bonus of {2} to access your new bonus.
Your balance will be reset to the state it was before.</val></t><t><key>freeRoundsNoWinnings</key><val>NO WINNINGS</val></t><t><key>freeRoundsNoWinningsPrize</key><val>Better luck next time!
Your free rounds have been completed.</val></t><t><key>freeRoundsPendingWins</key><val>You have no free rounds remaining.
You have an incomplete round on
{1}
Please complete it to finish your free rounds.</val></t><t><key>freeRoundsPopUpAcceptButtonLabel</key><val>Accept</val></t><t><key>freeRoundsPopUpDeclineButtonLabel</key><val>Decline</val></t><t><key>freeRoundStatusPanelTitleLabel</key><val>YOUR
FREE ROUNDS
EXPIRE ON</val></t><t><key>freeRoundsWinUpTo</key><val>Win up to {1}!</val></t><t><key>freeRoundsYouWon</key><val>You won {1} Free Rounds.</val></t><t><key>freeRoundsYouWonActiveValue</key><val>You have {2} Free Rounds remaining.
The offer will expire on {1}.
Good luck!</val></t><t><key>freeRoundsYouWonValue</key><val>Once you accept, you have {1} day/days
to play your Free Rounds.</val></t><t><key>freeRoundsYouWonValueOne</key><val>The offer expires on {1}.</val></t><t><key>freespinRemaining</key><val>REMAINING</val></t><t><key>freeSpinsBigTitle</key><val>CONGRATULATIONS</val></t><t><key>freeSpinsEndBtn</key><val>FINISH</val></t><t><key>freeSpinsLeftWithValue</key><val>{1} Free Spins left</val></t><t><key>freeSpinsRemainingValue</key><val>{1} FREE SPINS REMAINING</val></t><t><key>freeSpinsResumeBtn</key><val>RESUME</val></t><t><key>freeSpinsSpinsLeftLabel</key><val>SPINS LEFT</val></t><t><key>freeSpinsStartBtn</key><val>START</val></t><t><key>freeSpinsTotalWinLabel</key><val>TOTAL WIN</val></t><t><key>freeSpinsValue</key><val>{1} FREE SPINS</val></t><t><key>freeSpinsWinLabel</key><val>WIN</val></t><t><key>game_ip_blocked</key><val>Wagering for this game is not legal from your jurisdiction.</val></t><t><key>game_maintenance</key><val>Game is currently under maintenance! Please try again later!</val></t><t><key>gapTranslationERR022</key><val>Invalid secure token.</val></t><t><key>gapTranslationERR025</key><val>Insufficient funds.</val></t><t><key>gapTranslationERR026</key><val>Player account locked.</val></t><t><key>gapTranslationERR027</key><val>Wager limit exceeded.</val></t><t><key>gapTranslationERR1010</key><val>Player is already logged in. Duplicate login tried.</val></t><t><key>gapTranslationERR1011</key><val>Player account is blocked (too many log in attempts).</val></t><t><key>gapTranslationERR1012</key><val>Player inserted invalid pin.</val></t><t><key>gapTranslationERR1024</key><val>Gaming is disabled for this game type.</val></t><t><key>genericError</key><val>There was a connection problem. Please try again later.</val></t><t><key>historyForRealMoney</key><val>The game history is available only when playing for money.</val></t><t><key>infoMessageGoodLuck</key><val>Good luck !</val></t><t><key>infoMessageLastWinning</key><val>Last win: {1}</val></t><t><key>infoMessageWelcome</key><val>Welcome!</val></t><t><key>introExitIntroScreenButton</key><val>CONTINUE</val></t><t><key>IntroScreenDescription1_1</key><val>5 OR MORE SUN DISC SCATTERS</val></t><t><key>IntroScreenDescription1_2</key><val>TRIGGER AZTEC GOLD CASH RESPINS!</val></t><t><key>IntroScreenDescription1_3</key><val>FILL AN ENTIRE COLUMN
TO WIN THE MULTIPLIER</val></t><t><key>IntroScreenDescription1_4</key><val>WATCH OUT FOR MINI, MAJOR AND MEGA SUN DISC SCATTERS!</val></t><t><key>IntroScreenDescription1_5</key><val>ANY WIN TRIGGERS A CASCADE!</val></t><t><key>IntroScreenDescription1_6</key><val>WATCH OUT FOR MODIFIERS</val></t><t><key>IntroScreenDescription1_7</key><val>TRIGGERED ON ANY SPIN</val></t><t><key>IntroScreenDescription1_8</key><val>TRIGGERED ON ANY SPIN</val></t><t><key>IntroScreenDescription1_9</key><val>ANY WIN TRIGGERS
A CASCADE!</val></t><t><key>IntroScreenDescription2_1</key><val>CASCADING REELS!</val></t><t><key>IntroScreenDescription2_2</key><val>ANY WIN TRIGGERS A CASCADE!</val></t><t><key>IntroScreenDescription3_1</key><val>WATCH OUT FOR MODIFIERS</val></t><t><key>IntroScreenDescription3_2</key><val>TRIGGERED ON ANY SPIN</val></t><t><key>iSoftBetCopyrightLabel</key><val>TM&amp;© 2017 iSoftBet
All Rights Reserved.</val></t><t><key>jackpotNoticeInfo1</key><val>A player has won:</val></t><t><key>jackpotNoticeInfo2</key><val>at coin value {1}!</val></t><t><key>jackpotNoticeTitle</key><val>JACKPOT!</val></t><t><key>labelFreeSpin</key><val>Free Spin</val></t><t><key>labelFreeSpins</key><val>Free Spins</val></t><t><key>leftRespin</key><val>You have 1 free respin left!</val></t><t><key>leftRespins</key><val>You have {1} free respins left!</val></t><t><key>Megaways_Description1</key><val>Each spin can have up to 117,649 ways to win!</val></t><t><key>Megaways_Description2</key><val>Wins are awarded on left to right adjacent symbols regardless of size starting on reel 1.</val></t><t><key>Megaways_Description3</key><val>(Megaways under license from BTG)</val></t><t><key>menuAutoPlayButton</key><val>AUTO SPIN</val></t><t><key>menuBetButton</key><val>BET</val></t><t><key>menuBetPerLineValueButton</key><val>BET PER LINE:</val></t><t><key>menuBuyLabel</key><val>BUY</val></t><t><key>menuCoinValueButton</key><val>COIN VALUE</val></t><t><key>menuEffectsLabel</key><val>Effects Volume</val></t><t><key>menuFullscreenLabel</key><val>FULLSCREEN</val></t><t><key>menuGeneralLabel</key><val>General Volume</val></t><t><key>menuHistoryLabel</key><val>HISTORY</val></t><t><key>menuLabelSettings</key><val>SETTINGS</val></t><t><key>menuLeftHandedModeLabel</key><val>Left handed mode</val></t><t><key>menuLinesButton</key><val>LINES</val></t><t><key>menuMusicLabel</key><val>Music Volume</val></t><t><key>menuOffButton</key><val>OFF</val></t><t><key>menuOnButton</key><val>ON</val></t><t><key>menuPaytableButton</key><val>AZTEC GOLD MEGAWAYS™</val></t><t><key>menuRulesButton</key><val>RULES</val></t><t><key>menuSettingsHome</key><val>HOME</val></t><t><key>menuSoundButton</key><val>SOUND</val></t><t><key>menuSoundButtonLabel</key><val>&lt;p&gt;SOUND&lt;/p&gt;</val></t><t><key>menuStopAutoPlayButton</key><val>STOP AUTO SPIN</val></t><t><key>menuTotalBetButton</key><val>TOTAL BET (COINS)</val></t><t><key>menuTurboLabel</key><val>TURBO</val></t><t><key>menuTurboModeLabel</key><val>TURBO MODE</val></t><t><key>menuWinningLabel</key><val>Winning Sounds</val></t><t><key>menuWinningsLabel</key><val>WINNINGS</val></t><t><key>mobileCopyright</key><val>Game by iSoftBet</val></t><t><key>multiplier</key><val>MULTIPLIER</val></t><t><key>neverShowIntroLabel</key><val>Never show again</val></t><t><key>notEnoughMoney</key><val>You don’t have enough credit to make that bet. Please try a lower bet or visit the Cashier.</val></t><t><key>noWinningsMessage</key><val>No winnings!</val></t><t><key>oneByOneCashRespinsWin</key><val>You have won {1} Cash Respins!</val></t><t><key>oneByOneFreeGamesWin</key><val>You have won {1} Free Spins!</val></t><t><key>oneByOneLineWin</key><val>Line {1}: {image} = {2}</val></t><t><key>oneByOneProgressiveWin</key><val>JACKPOT: {image} X5 = {1}</val></t><t><key>oneByOneScatterWin</key><val>SCATTER: {image} = {1}</val></t><t><key>oneByOneWaysWin</key><val>{1} WAYS x {image} = {2}</val></t><t><key>paytableBasicRulesDescription</key><val>Select the COIN VALUE that you want to use.
This game is a MEGAWAYS™ slot with up to 117,649 winning ways.
Each spin will cost 20 x selected coin value.
Press on SPIN to start the game.
Use AUTO SPIN to set your own automatic play settings.
All winnings are paid from left to right except for SUN DISC SCATTERS.
Symbol wins are as per paytable, regardless of the size of the symbols.</val></t><t><key>paytableBasicRulesTitle</key><val>BASIC RULES</val></t><t><key>paytableDisplayRulesDescription</key><val>CREDIT indicates the amount of credit available according to the COIN VALUE you choose.
BALANCE indicates the amount of real money available.
BET indicates the amount that you will bet on the next spin.
WIN indicates the amount won in the previous games and it is already multiplied by the selected coin value.</val></t><t><key>paytableDisplayRulesTitle</key><val>DISPLAY</val></t><t><key>paytablePayoutsCoinValue</key><val>Payouts shown are in coins.
All payouts will be multiplied by the selected coin value.</val></t><t><key>paytablePayoutsInCoins</key><val>All wins begin with the left most reel and pay left to right on consecutive reels, except Sun Disc Scatter which pays any.</val></t><t><key>paytablePayoutsMultipliedByStake</key><val>Payouts are multiplied by stake</val></t><t><key>paytableTitleLines</key><val>LINES</val></t><t><key>paytableTitlePayouts</key><val>PAYOUTS</val></t><t><key>paytableTitlePayoutsHigh</key><val>PAYOUTS HIGH</val></t><t><key>paytableTitlePayoutsLow</key><val>PAYOUTS LOW</val></t><t><key>paytableTitlePayoutsMedium</key><val>PAYOUTS MEDIUM</val></t><t><key>paytableTitleRules</key><val>RULES</val></t><t><key>paytableTitleScatter</key><val>SUN DISC SCATTER</val></t><t><key>payTableVoid</key><val>Payments and game activity will be void in the event of malfunction.</val></t><t><key>popupRealityCheckCloseButtonLabel</key><val>Quit</val></t><t><key>popupRealityCheckContinueButtonLabel</key><val>Continue</val></t><t><key>popupRealityCheckHistoryButtonLabel</key><val>History</val></t><t><key>popupRealityCheckMessage</key><val>You have been playing for {1} minutes
extend session duration by (minutes):</val></t><t><key>popupRealityCheckTitleLabel</key><val>Duration Reminder</val></t><t><key>popupYouveWon</key><val>YOU'VE WON</val></t><t><key>popup_1</key><val>You have completed the required playthrough for your non-redeemable bonus. The remaining bonus amount {1} will be removed from your balance.</val></t><t><key>popup_2</key><val>Your bonus is now activated and an amount of {1} will be added to your balance</val></t><t><key>popup_3</key><val>Sorry, you have exceeded your set bet limit</val></t><t><key>popup_4</key><val>Sorry, you have exceeded your set limit on losses</val></t><t><key>popup_5</key><val>Sorry, you have exceeded your set time limit</val></t><t><key>pressToContinue</key><val>PRESS ANYWHERE TO CONTINUE</val></t><t><key>pressToContinue_MOBILE</key><val>TAP ANYWHERE TO CONTINUE</val></t><t><key>PTAztecGoldCashRespinsTitle</key><val>AZTEC GOLD CASH RESPINS</val></t><t><key>ptBackButton</key><val>BACK</val></t><t><key>PTBonusDescription</key><val>Wild substitutes for all symbols except Sun Disc Scatter</val></t><t><key>PTCascadingWinsTitle</key><val>CASCADING WINS</val></t><t><key>ptMalfunctionLabel</key><val>Payments and game activity will be void
in the event of malfunction.</val></t><t><key>ptRulesPageVoidPayments</key><val>Payments and game activity will be void in the event of malfunction.</val></t><t><key>PTWildDescription</key><val>5 or more Sun Disc Scatters trigger Aztec Gold Cash Respins</val></t><t><key>PT_ways_text_3</key><val>MULTIPLY THE NUMBER OF ADJACENT WINNING SYMBOLS ON EACH OF THE REELS TO GIVE THE TOTAL NUMBER OF WINNING WAYS … IN THE ABOVE EXAMPLE YOU HAVE 12:</val></t><t><key>PT_ways_text_4</key><val>2 x 3 x 1 x 2 = 12</val></t><t><key>PT_ways_text_5</key><val>THE WINNING SYMBOL PAYOUT IS MULTIPLIED BY THE
NUMBER OF WINNING WAYS TO GIVE THE TOTAL WIN:</val></t><t><key>PT_ways_text_6</key><val>TOTAL WINNINGS IN THIS EXAMPLE:</val></t><t><key>PT_ways_text_7</key><val>12 (ways) x 50 (payout) = 600 coins</val></t><t><key>PT_ways_text_8</key><val>Ways wins can be formed from multiple symbols on each spin &amp; cascade.</val></t><t><key>respinsDescriptionLabel</key><val>FILL A WHOLE REEL TO UNLOCK THE MULTIPLIER</val></t><t><key>respinsNowLockedLabel</key><val>NOW LOCKED</val></t><t><key>respinsTriggerLabel</key><val>YOU'VE TRIGGERED</val></t><t><key>resumeFreeSpinsInfoBoxMessage</key><val>You have {1} Free Spins. Click to begin!</val></t><t><key>resumeFreeSpinsNoneLeftInfoBoxMessage</key><val>Click to begin!</val></t><t><key>showAllCashRespins</key><val>Cash Respins Awarded</val></t><t><key>showAllFreeGames</key><val>{1} FREE SPINS</val></t><t><key>showAllLineWin</key><val>lines {1} !</val></t><t><key>showAllProgressive</key><val>jackpot: {1}</val></t><t><key>showAllRespins</key><val>{1} free respins</val></t><t><key>showAllScatter</key><val>{1} from scatters</val></t><t><key>showAllSingleLineWin</key><val>line {1} !</val></t><t><key>showAllSingleWayWin</key><val>WAY = {1}</val></t><t><key>showAllWaysWays</key><val>WAYS</val></t><t><key>showAllWaysWin</key><val>WAYS = {1}</val></t><t><key>showAllWayWay</key><val>WAY</val></t><t><key>startFreeSpinsInfoBoxMessage</key><val>You won {1} Free Spins. Click to begin!</val></t><t><key>stripBalanceLabel</key><val>BALANCE:</val></t><t><key>stripBonusBalanceLabel</key><val>BONUS BALANCE: {1} (BONUS CREDIT: {2})</val></t><t><key>stripCreditLabel</key><val>CREDIT:</val></t><t><key>stripTotalBetLabel</key><val>BET:</val></t><t><key>stripWinLabel</key><val>WIN:</val></t><t><key>uiBetInCoins</key><val>({1} coins)</val></t><t><key>uiBetSettingsLabel</key><val>BET SETTINGS</val></t><t><key>uiCoinValueButton</key><val>COIN VALUE</val></t><t><key>uiCoinValueLabel</key><val>COIN VALUE:</val></t><t><key>uiPaytableButton</key><val>PAYTABLE</val></t><t><key>uiTotalBet2Label</key><val>TOTAL BET:</val></t><t><key>uiTotalBetLabel</key><val>BET</val></t><t><key>uiWinLabel</key><val>WIN</val></t><t><key>unluckyText</key><val>SORRY</val></t><t><key>versionMaxBet</key><val>Maximum Bet:{1}</val></t><t><key>versionMinBet</key><val>Minimum Bet:{1}</val></t><t><key>warningLogoutMessage</key><val>You are now leaving the game.</val></t><t><key>warningMessageNoMoney</key><val>NOT ENOUGH MONEY</val></t><t><key>warningMessageNoMoneyContent</key><val>You don't have enough money to place the selected bet.</val></t><t><key>warningMessageNoMoneyRebuy</key><val>Please use the rebuy option.</val></t><t><key>youHaveMessage</key><val>YOU HAVE</val></t><t><key>youWonMessage</key><val>You won</val></t><t><key>youWonPopup</key><val>YOU'VE WON</val></t></translations>
